azure_lightning_flask/__init__.py
azure_lightning_flask/__main__.py
azure_lightning_flask/application.py
azure_lightning_flask/application_blueprint.py
azure_lightning_flask/helpers.py
azure_lightning_flask-0.0.1.dist-info/DESCRIPTION.rst
azure_lightning_flask-0.0.1.dist-info/METADATA
azure_lightning_flask-0.0.1.dist-info/RECORD
azure_lightning_flask-0.0.1.dist-info/WHEEL
azure_lightning_flask-0.0.1.dist-info/entry_points.txt
azure_lightning_flask-0.0.1.dist-info/metadata.json
azure_lightning_flask-0.0.1.dist-info/top_level.txt
tests/__init__.py
tests/application_tests.py
tests/helper_tests.py
tests/test_config.py
