Metadata-Version: 2.0
Name: azure-lightning-flask
Version: 0.0.1
Summary: Lightning deployment strategy on Azure with Flask
Home-page: UNKNOWN
Author: Hayden Demerson
Author-email: UNKNOWN
License: MIT
Platform: UNKNOWN
Classifier: License :: OSI Approved :: MIT License
Classifier: Framework :: Flask
Classifier: Programming Language :: Python
Classifier: Programming Language :: Python :: 2.7
Requires-Dist: Flask-Env (>=1.0.1)
Requires-Dist: Flask (>=0.12.0)
Requires-Dist: azure-common (>=1.0.0)
Requires-Dist: azure-cosmosdb-table (>=1.0.0)
